Metadata-Version: 2.1
Name: unify-document-class
Version: 0.0
Summary: Unified classes representing the structural elements of a text document
Home-page: UNKNOWN
Author-email: slavamarcin@yandex.ru
License: UNKNOWN
Platform: UNKNOWN
